pykube/__init__.py
pykube/__main__.py
pykube/config.py
pykube/console.py
pykube/exceptions.py
pykube/http.py
pykube/mixins.py
pykube/objects.py
pykube/query.py
pykube/utils.py
new_pykube-26.1.0.dist-info/METADATA
new_pykube-26.1.0.dist-info/WHEEL
new_pykube-26.1.0.dist-info/licenses/LICENSE
new_pykube-26.1.0.dist-info/RECORD
