Metadata-Version: 2.4
Name: new-pykube
Version: 26.1.0
Summary: Python client library for Kubernetes
License: Apache
License-File: LICENSE
Author: Jonathan Mayer
Author-email: jonathan.mayer@telekom.de
Requires-Python: >=3.10,<4
Classifier: Development Status :: 5 - Production/Stable
Classifier: Environment :: Web Environment
Classifier: Intended Audience :: Developers
Classifier: License :: OSI Approved :: Apache Software License
Classifier: License :: Other/Proprietary License
Classifier: Operating System :: OS Independent
Classifier: Programming Language :: Python
Classifier: Programming Language :: Python :: 3
Classifier: Programming Language :: Python :: 3.10
Classifier: Programming Language :: Python :: 3.11
Classifier: Programming Language :: Python :: 3.12
Classifier: Programming Language :: Python :: 3.13
Classifier: Programming Language :: Python :: 3.14
Classifier: Programming Language :: Python :: 3 :: Only
Provides-Extra: gcp
Provides-Extra: oidc
Requires-Dist: google-auth ; extra == "gcp"
Requires-Dist: jsonpath-ng ; extra == "gcp"
Requires-Dist: pyyaml
Requires-Dist: requests (>=2.12)
Requires-Dist: requests-oauthlib (>=1.3.0,<2.0.0) ; extra == "oidc"
Requires-Dist: urllib3 (>=1.26.9)
Project-URL: Homepage, https://github.com/caas-team/new-pykube
